MANIFEST.in
README.md
requirements.txt
setup.py
test_requirements.txt
version.txt
cloudshell/__init__.py
cloudshell/cisco/__init__.py
cloudshell/cisco/aci/__init__.py
cloudshell/cisco/aci/controller/__init__.py
cloudshell/cisco/aci/controller/configuration_attributes_structure.py
cloudshell/cisco/aci/controller/api/__init__.py
cloudshell/cisco/aci/controller/api/client.py
cloudshell_cisco_aci.egg-info/PKG-INFO
cloudshell_cisco_aci.egg-info/SOURCES.txt
cloudshell_cisco_aci.egg-info/dependency_links.txt
cloudshell_cisco_aci.egg-info/requires.txt
cloudshell_cisco_aci.egg-info/top_level.txt
tests/__init__.py